{"origin_city":"Maryhaven","dest_city":"Marieside","departure_date_time":"2020-02-26 22:38:00","arrival_date_time":"2020-02-29 10:28:00","passengers":462.0,"total_minutes":3590.0,"hours":11,"minutes":50,"time_combined":"11:50"}
{"origin_city":"Maryhaven","dest_city":"New Sandra","departure_date_time":"2020-02-26 21:56:00","arrival_date_time":"2020-02-29 15:42:00","passengers":370.0,"total_minutes":3946.0,"hours":17,"minutes":46,"time_combined":"17:46"}
{"origin_city":"Maryhaven","dest_city":"Mccannport","departure_date_time":"2020-02-08 20:21:00","arrival_date_time":"2020-02-11 12:49:00","passengers":70.0,"total_minutes":3868.0,"hours":16,"minutes":28,"time_combined":"16:28"}
{"origin_city":"Maryhaven","dest_city":"Keyberg","departure_date_time":"2020-02-06 01:01:00","arrival_date_time":"2020-02-08 19:19:00","passengers":473.0,"total_minutes":3978.0,"hours":18,"minutes":18,"time_combined":"18:18"}
{"origin_city":"Maryhaven","dest_city":"South Michaelastad","departure_date_time":"2020-02-19 07:56:00","arrival_date_time":"2020-02-22 06:00:00","passengers":652.0,"total_minutes":4204.0,"hours":22,"minutes":4,"time_combined":"22:4"}
{"origin_city":"Maryhaven","dest_city":"Laurenbury","departure_date_time":"2020-02-09 22:21:00","arrival_date_time":"2020-02-12 07:11:00","passengers":512.0,"total_minutes":3410.0,"hours":8,"minutes":50,"time_combined":"8:50"}
{"origin_city":"Maryhaven","dest_city":"North April","departure_date_time":"2020-02-22 10:44:00","arrival_date_time":"2020-02-23 12:05:00","passengers":720.0,"total_minutes":1521.0,"hours":1,"minutes":21,"time_combined":"1:21"}
{"origin_city":"Maryhaven","dest_city":"Lake Julie","departure_date_time":"2020-02-07 17:25:00","arrival_date_time":"2020-02-08 17:40:00","passengers":247.0,"total_minutes":1455.0,"hours":0,"minutes":15,"time_combined":"0:15"}
{"origin_city":"Maryhaven","dest_city":"Marieside","departure_date_time":"2020-02-03 14:59:00","arrival_date_time":"2020-02-06 12:29:00","passengers":459.0,"total_minutes":4170.0,"hours":21,"minutes":30,"time_combined":"21:30"}
{"origin_city":"Maryhaven","dest_city":"Mikeview","departure_date_time":"2020-02-25 04:49:00","arrival_date_time":"2020-02-26 15:35:00","passengers":512.0,"total_minutes":2086.0,"hours":10,"minutes":46,"time_combined":"10:46"}
{"origin_city":"Maryhaven","dest_city":"New Josehaven","departure_date_time":"2020-02-25 20:52:00","arrival_date_time":"2020-02-27 06:35:00","passengers":522.0,"total_minutes":2023.0,"hours":9,"minutes":43,"time_combined":"9:43"}
{"origin_city":"Maryhaven","dest_city":"East Gregorychester","departure_date_time":"2020-02-27 21:24:00","arrival_date_time":"2020-03-01 01:44:00","passengers":611.0,"total_minutes":3140.0,"hours":4,"minutes":20,"time_combined":"4:20"}
{"origin_city":"Maryhaven","dest_city":"New Josehaven","departure_date_time":"2020-02-07 02:56:00","arrival_date_time":"2020-02-08 10:38:00","passengers":436.0,"total_minutes":1902.0,"hours":7,"minutes":42,"time_combined":"7:42"}
{"origin_city":"Maryhaven","dest_city":"New Sandra","departure_date_time":"2020-02-15 03:56:00","arrival_date_time":"2020-02-17 04:37:00","passengers":754.0,"total_minutes":2921.0,"hours":0,"minutes":41,"time_combined":"0:41"}
{"origin_city":"Maryhaven","dest_city":"New Sandra","departure_date_time":"2020-02-26 23:01:00","arrival_date_time":"2020-02-29 22:42:00","passengers":364.0,"total_minutes":4301.0,"hours":23,"minutes":41,"time_combined":"23:41"}
{"origin_city":"Maryhaven","dest_city":"New Karishire","departure_date_time":"2020-02-26 16:23:00","arrival_date_time":"2020-02-27 17:07:00","passengers":368.0,"total_minutes":1484.0,"hours":0,"minutes":44,"time_combined":"0:44"}
{"origin_city":"Maryhaven","dest_city":"Laurenbury","departure_date_time":"2020-02-09 15:30:00","arrival_date_time":"2020-02-11 06:18:00","passengers":736.0,"total_minutes":2328.0,"hours":14,"minutes":48,"time_combined":"14:48"}
{"origin_city":"Maryhaven","dest_city":"Maryhaven","departure_date_time":"2020-02-08 18:07:00","arrival_date_time":"2020-02-09 23:43:00","passengers":467.0,"total_minutes":1776.0,"hours":5,"minutes":36,"time_combined":"5:36"}
{"origin_city":"Maryhaven","dest_city":"Santanaport","departure_date_time":"2020-02-18 04:03:00","arrival_date_time":"2020-02-19 10:09:00","passengers":484.0,"total_minutes":1806.0,"hours":6,"minutes":6,"time_combined":"6:6"}
{"origin_city":"Maryhaven","dest_city":"New Brian","departure_date_time":"2020-02-05 10:16:00","arrival_date_time":"2020-02-06 23:16:00","passengers":144.0,"total_minutes":2220.0,"hours":13,"minutes":0,"time_combined":"13:0"}
{"origin_city":"Maryhaven","dest_city":"Mikeview","departure_date_time":"2020-02-20 21:13:00","arrival_date_time":"2020-02-23 06:42:00","passengers":529.0,"total_minutes":3449.0,"hours":9,"minutes":29,"time_combined":"9:29"}
{"origin_city":"Maryhaven","dest_city":"West Carmen","departure_date_time":"2020-02-10 00:24:00","arrival_date_time":"2020-02-12 19:55:00","passengers":117.0,"total_minutes":4051.0,"hours":19,"minutes":31,"time_combined":"19:31"}
{"origin_city":"Maryhaven","dest_city":"East Michaelfort","departure_date_time":"2020-02-12 06:13:00","arrival_date_time":"2020-02-13 20:18:00","passengers":582.0,"total_minutes":2285.0,"hours":14,"minutes":5,"time_combined":"14:5"}
{"origin_city":"Maryhaven","dest_city":"Lake Julie","departure_date_time":"2020-02-27 18:49:00","arrival_date_time":"2020-02-29 21:14:00","passengers":197.0,"total_minutes":3025.0,"hours":2,"minutes":25,"time_combined":"2:25"}
{"origin_city":"Maryhaven","dest_city":"Huntershire","departure_date_time":"2020-02-22 14:43:00","arrival_date_time":"2020-02-24 19:24:00","passengers":168.0,"total_minutes":3161.0,"hours":4,"minutes":41,"time_combined":"4:41"}
{"origin_city":"Maryhaven","dest_city":"Santanaport","departure_date_time":"2020-02-14 16:29:00","arrival_date_time":"2020-02-17 11:58:00","passengers":740.0,"total_minutes":4049.0,"hours":19,"minutes":29,"time_combined":"19:29"}
{"origin_city":"Maryhaven","dest_city":"Laurenbury","departure_date_time":"2020-02-25 02:15:00","arrival_date_time":"2020-02-26 17:53:00","passengers":583.0,"total_minutes":2378.0,"hours":15,"minutes":38,"time_combined":"15:38"}
{"origin_city":"Maryhaven","dest_city":"New Josehaven","departure_date_time":"2020-02-18 19:41:00","arrival_date_time":"2020-02-20 01:56:00","passengers":294.0,"total_minutes":1815.0,"hours":6,"minutes":15,"time_combined":"6:15"}
{"origin_city":"Maryhaven","dest_city":"Marieside","departure_date_time":"2020-02-03 19:16:00","arrival_date_time":"2020-02-05 14:10:00","passengers":469.0,"total_minutes":2574.0,"hours":18,"minutes":54,"time_combined":"18:54"}
{"origin_city":"Maryhaven","dest_city":"Millershire","departure_date_time":"2020-02-19 00:13:00","arrival_date_time":"2020-02-21 07:41:00","passengers":558.0,"total_minutes":3328.0,"hours":7,"minutes":28,"time_combined":"7:28"}
{"origin_city":"Maryhaven","dest_city":"East Danielton","departure_date_time":"2020-02-16 02:27:00","arrival_date_time":"2020-02-18 17:04:00","passengers":99.0,"total_minutes":3757.0,"hours":14,"minutes":37,"time_combined":"14:37"}
{"origin_city":"Maryhaven","dest_city":"Davismouth","departure_date_time":"2020-02-18 04:53:00","arrival_date_time":"2020-02-19 14:44:00","passengers":130.0,"total_minutes":2031.0,"hours":9,"minutes":51,"time_combined":"9:51"}
{"origin_city":"Maryhaven","dest_city":"Joelmouth","departure_date_time":"2020-02-08 10:22:00","arrival_date_time":"2020-02-09 19:07:00","passengers":237.0,"total_minutes":1965.0,"hours":8,"minutes":45,"time_combined":"8:45"}
{"origin_city":"Maryhaven","dest_city":"Marieside","departure_date_time":"2020-02-22 10:25:00","arrival_date_time":"2020-02-24 12:16:00","passengers":226.0,"total_minutes":2991.0,"hours":1,"minutes":51,"time_combined":"1:51"}
{"origin_city":"Maryhaven","dest_city":"New Manuel","departure_date_time":"2020-02-24 04:57:00","arrival_date_time":"2020-02-26 16:53:00","passengers":697.0,"total_minutes":3596.0,"hours":11,"minutes":56,"time_combined":"11:56"}
{"origin_city":"Maryhaven","dest_city":"New Brian","departure_date_time":"2020-02-11 10:08:00","arrival_date_time":"2020-02-12 16:42:00","passengers":151.0,"total_minutes":1834.0,"hours":6,"minutes":34,"time_combined":"6:34"}
{"origin_city":"Maryhaven","dest_city":"New Sandra","departure_date_time":"2020-02-03 08:23:00","arrival_date_time":"2020-02-05 05:49:00","passengers":800.0,"total_minutes":2726.0,"hours":21,"minutes":26,"time_combined":"21:26"}
