{"origin_city":"Velezmouth","dest_city":"Thomasborough","departure_date_time":"2020-04-20 16:25:00","arrival_date_time":"2020-04-22 04:24:00","passengers":147.0,"total_minutes":2159.0,"hours":11,"minutes":59,"time_combined":"11:59"}
{"origin_city":"Velezmouth","dest_city":"North April","departure_date_time":"2020-04-03 01:44:00","arrival_date_time":"2020-04-05 10:12:00","passengers":156.0,"total_minutes":3388.0,"hours":8,"minutes":28,"time_combined":"8:28"}
{"origin_city":"Velezmouth","dest_city":"East William","departure_date_time":"2020-04-06 11:09:00","arrival_date_time":"2020-04-07 17:48:00","passengers":457.0,"total_minutes":1839.0,"hours":6,"minutes":39,"time_combined":"6:39"}
{"origin_city":"Velezmouth","dest_city":"New Brian","departure_date_time":"2020-04-09 19:43:00","arrival_date_time":"2020-04-12 01:41:00","passengers":581.0,"total_minutes":3238.0,"hours":5,"minutes":58,"time_combined":"5:58"}
{"origin_city":"Velezmouth","dest_city":"Joelmouth","departure_date_time":"2020-04-25 00:39:00","arrival_date_time":"2020-04-27 08:51:00","passengers":256.0,"total_minutes":3372.0,"hours":8,"minutes":12,"time_combined":"8:12"}
{"origin_city":"Velezmouth","dest_city":"Lake Randy","departure_date_time":"2020-04-09 12:37:00","arrival_date_time":"2020-04-12 04:37:00","passengers":691.0,"total_minutes":3840.0,"hours":16,"minutes":0,"time_combined":"16:0"}
{"origin_city":"Velezmouth","dest_city":"New Michele","departure_date_time":"2020-04-24 16:22:00","arrival_date_time":"2020-04-27 04:24:00","passengers":765.0,"total_minutes":3602.0,"hours":12,"minutes":2,"time_combined":"12:2"}
{"origin_city":"Velezmouth","dest_city":"South Megan","departure_date_time":"2020-04-09 06:22:00","arrival_date_time":"2020-04-10 17:11:00","passengers":457.0,"total_minutes":2089.0,"hours":10,"minutes":49,"time_combined":"10:49"}
{"origin_city":"Velezmouth","dest_city":"East Gregorychester","departure_date_time":"2020-04-05 15:13:00","arrival_date_time":"2020-04-08 02:26:00","passengers":188.0,"total_minutes":3553.0,"hours":11,"minutes":13,"time_combined":"11:13"}
{"origin_city":"Velezmouth","dest_city":"Keyberg","departure_date_time":"2020-04-26 23:19:00","arrival_date_time":"2020-04-28 13:02:00","passengers":606.0,"total_minutes":2263.0,"hours":13,"minutes":43,"time_combined":"13:43"}
{"origin_city":"Velezmouth","dest_city":"South Justinmouth","departure_date_time":"2020-04-08 05:08:00","arrival_date_time":"2020-04-09 07:29:00","passengers":650.0,"total_minutes":1581.0,"hours":2,"minutes":21,"time_combined":"2:21"}
{"origin_city":"Velezmouth","dest_city":"New Brian","departure_date_time":"2020-04-29 05:42:00","arrival_date_time":"2020-05-01 16:58:00","passengers":121.0,"total_minutes":3556.0,"hours":11,"minutes":16,"time_combined":"11:16"}
{"origin_city":"Velezmouth","dest_city":"West Carolynbury","departure_date_time":"2020-04-28 19:37:00","arrival_date_time":"2020-04-29 21:19:00","passengers":625.0,"total_minutes":1542.0,"hours":1,"minutes":42,"time_combined":"1:42"}
{"origin_city":"Velezmouth","dest_city":"New Manuel","departure_date_time":"2020-04-06 05:48:00","arrival_date_time":"2020-04-08 02:31:00","passengers":608.0,"total_minutes":2683.0,"hours":20,"minutes":43,"time_combined":"20:43"}
{"origin_city":"Velezmouth","dest_city":"North Jeffreyberg","departure_date_time":"2020-04-25 09:47:00","arrival_date_time":"2020-04-27 06:05:00","passengers":767.0,"total_minutes":2658.0,"hours":20,"minutes":18,"time_combined":"20:18"}
{"origin_city":"Velezmouth","dest_city":"Marieside","departure_date_time":"2020-04-13 01:54:00","arrival_date_time":"2020-04-15 01:46:00","passengers":108.0,"total_minutes":2872.0,"hours":23,"minutes":52,"time_combined":"23:52"}
{"origin_city":"Velezmouth","dest_city":"Proctorfurt","departure_date_time":"2020-04-01 11:19:00","arrival_date_time":"2020-04-03 22:26:00","passengers":486.0,"total_minutes":3547.0,"hours":11,"minutes":7,"time_combined":"11:7"}
{"origin_city":"Velezmouth","dest_city":"Davismouth","departure_date_time":"2020-04-10 06:36:00","arrival_date_time":"2020-04-12 15:05:00","passengers":238.0,"total_minutes":3389.0,"hours":8,"minutes":29,"time_combined":"8:29"}
{"origin_city":"Velezmouth","dest_city":"West Carmen","departure_date_time":"2020-04-18 02:12:00","arrival_date_time":"2020-04-19 22:08:00","passengers":514.0,"total_minutes":2636.0,"hours":19,"minutes":56,"time_combined":"19:56"}
{"origin_city":"Velezmouth","dest_city":"Timothyburgh","departure_date_time":"2020-04-21 11:02:00","arrival_date_time":"2020-04-22 14:16:00","passengers":731.0,"total_minutes":1634.0,"hours":3,"minutes":14,"time_combined":"3:14"}
{"origin_city":"Velezmouth","dest_city":"East William","departure_date_time":"2020-04-29 03:06:00","arrival_date_time":"2020-05-01 08:11:00","passengers":640.0,"total_minutes":3185.0,"hours":5,"minutes":5,"time_combined":"5:5"}
{"origin_city":"Velezmouth","dest_city":"Mccannport","departure_date_time":"2020-04-26 08:18:00","arrival_date_time":"2020-04-28 22:29:00","passengers":380.0,"total_minutes":3731.0,"hours":14,"minutes":11,"time_combined":"14:11"}
{"origin_city":"Velezmouth","dest_city":"South Megan","departure_date_time":"2020-04-06 16:12:00","arrival_date_time":"2020-04-08 07:26:00","passengers":676.0,"total_minutes":2354.0,"hours":15,"minutes":14,"time_combined":"15:14"}
{"origin_city":"Velezmouth","dest_city":"Velezmouth","departure_date_time":"2020-04-26 16:03:00","arrival_date_time":"2020-04-27 19:11:00","passengers":127.0,"total_minutes":1628.0,"hours":3,"minutes":8,"time_combined":"3:8"}
{"origin_city":"Velezmouth","dest_city":"Mccannport","departure_date_time":"2020-04-13 22:42:00","arrival_date_time":"2020-04-15 09:50:00","passengers":722.0,"total_minutes":2108.0,"hours":11,"minutes":8,"time_combined":"11:8"}
{"origin_city":"Velezmouth","dest_city":"New Michele","departure_date_time":"2020-04-13 20:45:00","arrival_date_time":"2020-04-16 07:51:00","passengers":216.0,"total_minutes":3546.0,"hours":11,"minutes":6,"time_combined":"11:6"}
{"origin_city":"Velezmouth","dest_city":"Huntershire","departure_date_time":"2020-04-02 20:25:00","arrival_date_time":"2020-04-05 13:19:00","passengers":164.0,"total_minutes":3894.0,"hours":16,"minutes":54,"time_combined":"16:54"}
{"origin_city":"Velezmouth","dest_city":"New Manuel","departure_date_time":"2020-04-02 07:16:00","arrival_date_time":"2020-04-03 08:42:00","passengers":173.0,"total_minutes":1526.0,"hours":1,"minutes":26,"time_combined":"1:26"}
{"origin_city":"Velezmouth","dest_city":"Velezmouth","departure_date_time":"2020-04-25 19:24:00","arrival_date_time":"2020-04-26 23:20:00","passengers":450.0,"total_minutes":1676.0,"hours":3,"minutes":56,"time_combined":"3:56"}
{"origin_city":"Velezmouth","dest_city":"Port Sharon","departure_date_time":"2020-04-17 16:19:00","arrival_date_time":"2020-04-19 12:34:00","passengers":593.0,"total_minutes":2655.0,"hours":20,"minutes":15,"time_combined":"20:15"}
{"origin_city":"Velezmouth","dest_city":"South Michaelastad","departure_date_time":"2020-04-24 15:02:00","arrival_date_time":"2020-04-27 07:49:00","passengers":316.0,"total_minutes":3887.0,"hours":16,"minutes":47,"time_combined":"16:47"}
{"origin_city":"Velezmouth","dest_city":"Lake Randy","departure_date_time":"2020-04-14 12:32:00","arrival_date_time":"2020-04-16 17:52:00","passengers":67.0,"total_minutes":3200.0,"hours":5,"minutes":20,"time_combined":"5:20"}
{"origin_city":"Velezmouth","dest_city":"Lake Julie","departure_date_time":"2020-04-19 09:16:00","arrival_date_time":"2020-04-21 10:44:00","passengers":139.0,"total_minutes":2968.0,"hours":1,"minutes":28,"time_combined":"1:28"}
{"origin_city":"Velezmouth","dest_city":"New Sandra","departure_date_time":"2020-04-08 11:10:00","arrival_date_time":"2020-04-09 16:14:00","passengers":157.0,"total_minutes":1744.0,"hours":5,"minutes":4,"time_combined":"5:4"}
{"origin_city":"Velezmouth","dest_city":"New Michele","departure_date_time":"2020-04-28 07:44:00","arrival_date_time":"2020-04-30 08:13:00","passengers":698.0,"total_minutes":2909.0,"hours":0,"minutes":29,"time_combined":"0:29"}
{"origin_city":"Velezmouth","dest_city":"Pearsonberg","departure_date_time":"2020-04-02 11:23:00","arrival_date_time":"2020-04-04 23:29:00","passengers":615.0,"total_minutes":3606.0,"hours":12,"minutes":6,"time_combined":"12:6"}
{"origin_city":"Velezmouth","dest_city":"West Jorgeville","departure_date_time":"2020-04-03 19:24:00","arrival_date_time":"2020-04-05 23:21:00","passengers":689.0,"total_minutes":3117.0,"hours":3,"minutes":57,"time_combined":"3:57"}
{"origin_city":"Velezmouth","dest_city":"West Carolynbury","departure_date_time":"2020-04-12 02:23:00","arrival_date_time":"2020-04-14 00:58:00","passengers":635.0,"total_minutes":2795.0,"hours":22,"minutes":35,"time_combined":"22:35"}
{"origin_city":"Velezmouth","dest_city":"West Charlesshire","departure_date_time":"2020-04-23 10:30:00","arrival_date_time":"2020-04-25 02:30:00","passengers":622.0,"total_minutes":2400.0,"hours":16,"minutes":0,"time_combined":"16:0"}
{"origin_city":"Velezmouth","dest_city":"West Matthewport","departure_date_time":"2020-04-25 11:48:00","arrival_date_time":"2020-04-27 10:44:00","passengers":308.0,"total_minutes":2816.0,"hours":22,"minutes":56,"time_combined":"22:56"}
{"origin_city":"Velezmouth","dest_city":"New Karishire","departure_date_time":"2020-04-22 02:18:00","arrival_date_time":"2020-04-23 08:25:00","passengers":759.0,"total_minutes":1807.0,"hours":6,"minutes":7,"time_combined":"6:7"}
