{"origin_city":"Keyberg","dest_city":"Lake Randy","departure_date_time":"2020-09-24 03:27:00","arrival_date_time":"2020-09-26 06:21:00","passengers":670.0,"total_minutes":3054.0,"hours":2,"minutes":54,"time_combined":"2:54"}
{"origin_city":"Keyberg","dest_city":"New Sandra","departure_date_time":"2020-09-03 20:58:00","arrival_date_time":"2020-09-06 16:17:00","passengers":363.0,"total_minutes":4039.0,"hours":19,"minutes":19,"time_combined":"19:19"}
{"origin_city":"Keyberg","dest_city":"West Carmen","departure_date_time":"2020-09-22 01:57:00","arrival_date_time":"2020-09-23 23:47:00","passengers":798.0,"total_minutes":2750.0,"hours":21,"minutes":50,"time_combined":"21:50"}
{"origin_city":"Keyberg","dest_city":"Mccannport","departure_date_time":"2020-09-28 10:15:00","arrival_date_time":"2020-09-29 18:55:00","passengers":748.0,"total_minutes":1960.0,"hours":8,"minutes":40,"time_combined":"8:40"}
{"origin_city":"Keyberg","dest_city":"Proctorfurt","departure_date_time":"2020-09-22 14:31:00","arrival_date_time":"2020-09-24 01:05:00","passengers":716.0,"total_minutes":2074.0,"hours":10,"minutes":34,"time_combined":"10:34"}
{"origin_city":"Keyberg","dest_city":"East Gregorychester","departure_date_time":"2020-09-22 03:24:00","arrival_date_time":"2020-09-24 09:17:00","passengers":315.0,"total_minutes":3233.0,"hours":5,"minutes":53,"time_combined":"5:53"}
{"origin_city":"Keyberg","dest_city":"South Megan","departure_date_time":"2020-09-20 01:48:00","arrival_date_time":"2020-09-21 05:16:00","passengers":593.0,"total_minutes":1648.0,"hours":3,"minutes":28,"time_combined":"3:28"}
{"origin_city":"Keyberg","dest_city":"Jenniferborough","departure_date_time":"2020-09-26 21:19:00","arrival_date_time":"2020-09-29 14:02:00","passengers":455.0,"total_minutes":3883.0,"hours":16,"minutes":43,"time_combined":"16:43"}
{"origin_city":"Keyberg","dest_city":"South Megan","departure_date_time":"2020-09-24 17:56:00","arrival_date_time":"2020-09-26 13:30:00","passengers":316.0,"total_minutes":2614.0,"hours":19,"minutes":34,"time_combined":"19:34"}
{"origin_city":"Keyberg","dest_city":"Millershire","departure_date_time":"2020-09-11 08:47:00","arrival_date_time":"2020-09-12 17:46:00","passengers":213.0,"total_minutes":1979.0,"hours":8,"minutes":59,"time_combined":"8:59"}
{"origin_city":"Keyberg","dest_city":"Lake Randy","departure_date_time":"2020-09-19 22:27:00","arrival_date_time":"2020-09-22 07:57:00","passengers":750.0,"total_minutes":3450.0,"hours":9,"minutes":30,"time_combined":"9:30"}
{"origin_city":"Keyberg","dest_city":"East Gregorychester","departure_date_time":"2020-09-15 21:22:00","arrival_date_time":"2020-09-17 11:45:00","passengers":560.0,"total_minutes":2303.0,"hours":14,"minutes":23,"time_combined":"14:23"}
{"origin_city":"Keyberg","dest_city":"West Jason","departure_date_time":"2020-09-11 18:17:00","arrival_date_time":"2020-09-14 02:10:00","passengers":273.0,"total_minutes":3353.0,"hours":7,"minutes":53,"time_combined":"7:53"}
{"origin_city":"Keyberg","dest_city":"East Gregorychester","departure_date_time":"2020-09-25 19:59:00","arrival_date_time":"2020-09-28 03:58:00","passengers":462.0,"total_minutes":3359.0,"hours":7,"minutes":59,"time_combined":"7:59"}
{"origin_city":"Keyberg","dest_city":"Keyberg","departure_date_time":"2020-09-26 03:16:00","arrival_date_time":"2020-09-28 22:22:00","passengers":360.0,"total_minutes":4026.0,"hours":19,"minutes":6,"time_combined":"19:6"}
{"origin_city":"Keyberg","dest_city":"Jenniferborough","departure_date_time":"2020-09-28 09:29:00","arrival_date_time":"2020-09-30 00:30:00","passengers":53.0,"total_minutes":2341.0,"hours":15,"minutes":1,"time_combined":"15:1"}
{"origin_city":"Keyberg","dest_city":"Jenniferborough","departure_date_time":"2020-09-14 05:00:00","arrival_date_time":"2020-09-15 12:28:00","passengers":385.0,"total_minutes":1888.0,"hours":7,"minutes":28,"time_combined":"7:28"}
{"origin_city":"Keyberg","dest_city":"Proctorfurt","departure_date_time":"2020-09-05 09:12:00","arrival_date_time":"2020-09-06 12:48:00","passengers":66.0,"total_minutes":1656.0,"hours":3,"minutes":36,"time_combined":"3:36"}
{"origin_city":"Keyberg","dest_city":"Timothyburgh","departure_date_time":"2020-09-15 09:13:00","arrival_date_time":"2020-09-16 19:03:00","passengers":475.0,"total_minutes":2030.0,"hours":9,"minutes":50,"time_combined":"9:50"}
{"origin_city":"Keyberg","dest_city":"Port Sharon","departure_date_time":"2020-09-12 09:59:00","arrival_date_time":"2020-09-14 16:13:00","passengers":235.0,"total_minutes":3254.0,"hours":6,"minutes":14,"time_combined":"6:14"}
{"origin_city":"Keyberg","dest_city":"North April","departure_date_time":"2020-09-27 19:59:00","arrival_date_time":"2020-09-30 10:07:00","passengers":489.0,"total_minutes":3728.0,"hours":14,"minutes":8,"time_combined":"14:8"}
{"origin_city":"Keyberg","dest_city":"Grantfort","departure_date_time":"2020-09-19 02:54:00","arrival_date_time":"2020-09-20 03:15:00","passengers":538.0,"total_minutes":1461.0,"hours":0,"minutes":21,"time_combined":"0:21"}
{"origin_city":"Keyberg","dest_city":"West Jason","departure_date_time":"2020-09-02 01:07:00","arrival_date_time":"2020-09-03 12:34:00","passengers":301.0,"total_minutes":2127.0,"hours":11,"minutes":27,"time_combined":"11:27"}
{"origin_city":"Keyberg","dest_city":"West Matthewport","departure_date_time":"2020-09-28 17:10:00","arrival_date_time":"2020-10-01 07:28:00","passengers":304.0,"total_minutes":3738.0,"hours":14,"minutes":18,"time_combined":"14:18"}
{"origin_city":"Keyberg","dest_city":"East William","departure_date_time":"2020-09-22 16:24:00","arrival_date_time":"2020-09-25 11:19:00","passengers":114.0,"total_minutes":4015.0,"hours":18,"minutes":55,"time_combined":"18:55"}
{"origin_city":"Keyberg","dest_city":"New Karishire","departure_date_time":"2020-09-24 14:25:00","arrival_date_time":"2020-09-27 01:24:00","passengers":449.0,"total_minutes":3539.0,"hours":10,"minutes":59,"time_combined":"10:59"}
{"origin_city":"Keyberg","dest_city":"Grantfort","departure_date_time":"2020-09-11 05:12:00","arrival_date_time":"2020-09-12 21:24:00","passengers":726.0,"total_minutes":2412.0,"hours":16,"minutes":12,"time_combined":"16:12"}
{"origin_city":"Keyberg","dest_city":"West Jorgeville","departure_date_time":"2020-09-24 03:22:00","arrival_date_time":"2020-09-27 03:00:00","passengers":159.0,"total_minutes":4298.0,"hours":23,"minutes":38,"time_combined":"23:38"}
{"origin_city":"Keyberg","dest_city":"South Justinmouth","departure_date_time":"2020-09-20 23:46:00","arrival_date_time":"2020-09-23 04:29:00","passengers":150.0,"total_minutes":3163.0,"hours":4,"minutes":43,"time_combined":"4:43"}
{"origin_city":"Keyberg","dest_city":"West Jason","departure_date_time":"2020-09-02 05:12:00","arrival_date_time":"2020-09-04 01:23:00","passengers":667.0,"total_minutes":2651.0,"hours":20,"minutes":11,"time_combined":"20:11"}
{"origin_city":"Keyberg","dest_city":"Proctorfurt","departure_date_time":"2020-09-30 00:03:00","arrival_date_time":"2020-10-01 08:45:00","passengers":105.0,"total_minutes":1962.0,"hours":8,"minutes":42,"time_combined":"8:42"}
{"origin_city":"Keyberg","dest_city":"New Brian","departure_date_time":"2020-09-13 11:39:00","arrival_date_time":"2020-09-14 20:18:00","passengers":517.0,"total_minutes":1959.0,"hours":8,"minutes":39,"time_combined":"8:39"}
{"origin_city":"Keyberg","dest_city":"New Brian","departure_date_time":"2020-09-07 21:39:00","arrival_date_time":"2020-09-08 23:18:00","passengers":465.0,"total_minutes":1539.0,"hours":1,"minutes":39,"time_combined":"1:39"}
{"origin_city":"Keyberg","dest_city":"Grantfort","departure_date_time":"2020-09-23 19:36:00","arrival_date_time":"2020-09-26 03:18:00","passengers":281.0,"total_minutes":3342.0,"hours":7,"minutes":42,"time_combined":"7:42"}
{"origin_city":"Keyberg","dest_city":"Timothyburgh","departure_date_time":"2020-09-23 01:52:00","arrival_date_time":"2020-09-25 01:02:00","passengers":528.0,"total_minutes":2830.0,"hours":23,"minutes":10,"time_combined":"23:10"}
{"origin_city":"Keyberg","dest_city":"West Carolynbury","departure_date_time":"2020-09-05 14:22:00","arrival_date_time":"2020-09-07 22:51:00","passengers":178.0,"total_minutes":3389.0,"hours":8,"minutes":29,"time_combined":"8:29"}
{"origin_city":"Keyberg","dest_city":"Hernandezburgh","departure_date_time":"2020-09-13 05:12:00","arrival_date_time":"2020-09-15 10:48:00","passengers":708.0,"total_minutes":3216.0,"hours":5,"minutes":36,"time_combined":"5:36"}
{"origin_city":"Keyberg","dest_city":"Jonathonhaven","departure_date_time":"2020-09-13 10:32:00","arrival_date_time":"2020-09-16 00:48:00","passengers":567.0,"total_minutes":3736.0,"hours":14,"minutes":16,"time_combined":"14:16"}
{"origin_city":"Keyberg","dest_city":"Mccannport","departure_date_time":"2020-09-22 14:06:00","arrival_date_time":"2020-09-24 10:40:00","passengers":216.0,"total_minutes":2674.0,"hours":20,"minutes":34,"time_combined":"20:34"}
{"origin_city":"Keyberg","dest_city":"Hernandezburgh","departure_date_time":"2020-09-21 20:19:00","arrival_date_time":"2020-09-24 15:40:00","passengers":602.0,"total_minutes":4041.0,"hours":19,"minutes":21,"time_combined":"19:21"}
{"origin_city":"Keyberg","dest_city":"West Carmen","departure_date_time":"2020-09-15 07:39:00","arrival_date_time":"2020-09-17 06:19:00","passengers":541.0,"total_minutes":2800.0,"hours":22,"minutes":40,"time_combined":"22:40"}
{"origin_city":"Keyberg","dest_city":"New Michele","departure_date_time":"2020-09-29 14:04:00","arrival_date_time":"2020-10-02 03:56:00","passengers":784.0,"total_minutes":3712.0,"hours":13,"minutes":52,"time_combined":"13:52"}
{"origin_city":"Keyberg","dest_city":"West Carmen","departure_date_time":"2020-09-02 10:47:00","arrival_date_time":"2020-09-03 21:26:00","passengers":188.0,"total_minutes":2079.0,"hours":10,"minutes":39,"time_combined":"10:39"}
{"origin_city":"Keyberg","dest_city":"East Maria","departure_date_time":"2020-09-06 14:02:00","arrival_date_time":"2020-09-09 05:53:00","passengers":489.0,"total_minutes":3831.0,"hours":15,"minutes":51,"time_combined":"15:51"}
{"origin_city":"Keyberg","dest_city":"Grantfort","departure_date_time":"2020-09-26 23:14:00","arrival_date_time":"2020-09-28 02:30:00","passengers":697.0,"total_minutes":1636.0,"hours":3,"minutes":16,"time_combined":"3:16"}
