{"origin_city":"Pearsonberg","dest_city":"New Karishire","departure_date_time":"2020-11-13 09:55:00","arrival_date_time":"2020-11-16 01:58:00","passengers":365.0,"total_minutes":3843.0,"hours":16,"minutes":3,"time_combined":"16:3"}
{"origin_city":"Pearsonberg","dest_city":"Marieside","departure_date_time":"2020-11-07 10:09:00","arrival_date_time":"2020-11-09 04:19:00","passengers":765.0,"total_minutes":2530.0,"hours":18,"minutes":10,"time_combined":"18:10"}
{"origin_city":"Pearsonberg","dest_city":"South Megan","departure_date_time":"2020-11-14 09:18:00","arrival_date_time":"2020-11-16 12:20:00","passengers":167.0,"total_minutes":3062.0,"hours":3,"minutes":2,"time_combined":"3:2"}
{"origin_city":"Pearsonberg","dest_city":"Hernandezburgh","departure_date_time":"2020-11-11 06:57:00","arrival_date_time":"2020-11-14 00:52:00","passengers":362.0,"total_minutes":3955.0,"hours":17,"minutes":55,"time_combined":"17:55"}
{"origin_city":"Pearsonberg","dest_city":"West Matthewport","departure_date_time":"2020-11-10 20:48:00","arrival_date_time":"2020-11-13 15:22:00","passengers":563.0,"total_minutes":3994.0,"hours":18,"minutes":34,"time_combined":"18:34"}
{"origin_city":"Pearsonberg","dest_city":"Chasefurt","departure_date_time":"2020-11-02 22:06:00","arrival_date_time":"2020-11-05 13:17:00","passengers":623.0,"total_minutes":3791.0,"hours":15,"minutes":11,"time_combined":"15:11"}
{"origin_city":"Pearsonberg","dest_city":"Velezmouth","departure_date_time":"2020-11-24 20:46:00","arrival_date_time":"2020-11-26 21:56:00","passengers":618.0,"total_minutes":2950.0,"hours":1,"minutes":10,"time_combined":"1:10"}
{"origin_city":"Pearsonberg","dest_city":"Laurenbury","departure_date_time":"2020-11-12 15:13:00","arrival_date_time":"2020-11-14 01:04:00","passengers":243.0,"total_minutes":2031.0,"hours":9,"minutes":51,"time_combined":"9:51"}
{"origin_city":"Pearsonberg","dest_city":"Port Sharon","departure_date_time":"2020-11-09 04:58:00","arrival_date_time":"2020-11-11 17:56:00","passengers":667.0,"total_minutes":3658.0,"hours":12,"minutes":58,"time_combined":"12:58"}
{"origin_city":"Pearsonberg","dest_city":"West Jason","departure_date_time":"2020-11-14 01:49:00","arrival_date_time":"2020-11-15 15:48:00","passengers":278.0,"total_minutes":2279.0,"hours":13,"minutes":59,"time_combined":"13:59"}
{"origin_city":"Pearsonberg","dest_city":"West Jason","departure_date_time":"2020-11-05 04:43:00","arrival_date_time":"2020-11-06 07:34:00","passengers":150.0,"total_minutes":1611.0,"hours":2,"minutes":51,"time_combined":"2:51"}
{"origin_city":"Pearsonberg","dest_city":"New Manuel","departure_date_time":"2020-11-24 16:13:00","arrival_date_time":"2020-11-25 23:27:00","passengers":636.0,"total_minutes":1874.0,"hours":7,"minutes":14,"time_combined":"7:14"}
{"origin_city":"Pearsonberg","dest_city":"West Charlesshire","departure_date_time":"2020-11-20 08:56:00","arrival_date_time":"2020-11-21 11:35:00","passengers":634.0,"total_minutes":1599.0,"hours":2,"minutes":39,"time_combined":"2:39"}
{"origin_city":"Pearsonberg","dest_city":"Port Sharon","departure_date_time":"2020-11-30 14:05:00","arrival_date_time":"2020-12-02 04:31:00","passengers":68.0,"total_minutes":2306.0,"hours":14,"minutes":26,"time_combined":"14:26"}
{"origin_city":"Pearsonberg","dest_city":"Keyberg","departure_date_time":"2020-11-01 12:06:00","arrival_date_time":"2020-11-03 13:07:00","passengers":87.0,"total_minutes":2941.0,"hours":1,"minutes":1,"time_combined":"1:1"}
{"origin_city":"Pearsonberg","dest_city":"Chasefurt","departure_date_time":"2020-11-21 04:00:00","arrival_date_time":"2020-11-23 19:57:00","passengers":279.0,"total_minutes":3837.0,"hours":15,"minutes":57,"time_combined":"15:57"}
{"origin_city":"Pearsonberg","dest_city":"West Carolynbury","departure_date_time":"2020-11-16 20:31:00","arrival_date_time":"2020-11-18 21:11:00","passengers":135.0,"total_minutes":2920.0,"hours":0,"minutes":40,"time_combined":"0:40"}
{"origin_city":"Pearsonberg","dest_city":"West Matthewport","departure_date_time":"2020-11-04 13:38:00","arrival_date_time":"2020-11-06 12:48:00","passengers":758.0,"total_minutes":2830.0,"hours":23,"minutes":10,"time_combined":"23:10"}
{"origin_city":"Pearsonberg","dest_city":"Millershire","departure_date_time":"2020-11-21 19:32:00","arrival_date_time":"2020-11-23 03:53:00","passengers":594.0,"total_minutes":1941.0,"hours":8,"minutes":21,"time_combined":"8:21"}
{"origin_city":"Pearsonberg","dest_city":"West Carolynbury","departure_date_time":"2020-11-18 15:57:00","arrival_date_time":"2020-11-20 10:47:00","passengers":384.0,"total_minutes":2570.0,"hours":18,"minutes":50,"time_combined":"18:50"}
{"origin_city":"Pearsonberg","dest_city":"Santanaport","departure_date_time":"2020-11-05 08:49:00","arrival_date_time":"2020-11-07 17:31:00","passengers":713.0,"total_minutes":3402.0,"hours":8,"minutes":42,"time_combined":"8:42"}
{"origin_city":"Pearsonberg","dest_city":"East Michaelfort","departure_date_time":"2020-11-03 16:30:00","arrival_date_time":"2020-11-06 14:44:00","passengers":727.0,"total_minutes":4214.0,"hours":22,"minutes":14,"time_combined":"22:14"}
{"origin_city":"Pearsonberg","dest_city":"Currystad","departure_date_time":"2020-11-01 15:26:00","arrival_date_time":"2020-11-04 09:44:00","passengers":749.0,"total_minutes":3978.0,"hours":18,"minutes":18,"time_combined":"18:18"}
{"origin_city":"Pearsonberg","dest_city":"New Karishire","departure_date_time":"2020-11-25 05:33:00","arrival_date_time":"2020-11-27 07:28:00","passengers":364.0,"total_minutes":2995.0,"hours":1,"minutes":55,"time_combined":"1:55"}
{"origin_city":"Pearsonberg","dest_city":"Santanaport","departure_date_time":"2020-11-27 05:09:00","arrival_date_time":"2020-11-28 15:00:00","passengers":494.0,"total_minutes":2031.0,"hours":9,"minutes":51,"time_combined":"9:51"}
{"origin_city":"Pearsonberg","dest_city":"New Michele","departure_date_time":"2020-11-08 22:18:00","arrival_date_time":"2020-11-10 12:49:00","passengers":61.0,"total_minutes":2311.0,"hours":14,"minutes":31,"time_combined":"14:31"}
{"origin_city":"Pearsonberg","dest_city":"West Carmen","departure_date_time":"2020-11-08 18:21:00","arrival_date_time":"2020-11-09 23:55:00","passengers":269.0,"total_minutes":1774.0,"hours":5,"minutes":34,"time_combined":"5:34"}
{"origin_city":"Pearsonberg","dest_city":"Joelmouth","departure_date_time":"2020-11-15 21:29:00","arrival_date_time":"2020-11-18 12:33:00","passengers":244.0,"total_minutes":3784.0,"hours":15,"minutes":4,"time_combined":"15:4"}
{"origin_city":"Pearsonberg","dest_city":"Thomasborough","departure_date_time":"2020-11-15 06:25:00","arrival_date_time":"2020-11-16 19:59:00","passengers":520.0,"total_minutes":2254.0,"hours":13,"minutes":34,"time_combined":"13:34"}
{"origin_city":"Pearsonberg","dest_city":"Currystad","departure_date_time":"2020-11-14 16:40:00","arrival_date_time":"2020-11-15 19:21:00","passengers":86.0,"total_minutes":1601.0,"hours":2,"minutes":41,"time_combined":"2:41"}
{"origin_city":"Pearsonberg","dest_city":"West Carmen","departure_date_time":"2020-11-25 22:53:00","arrival_date_time":"2020-11-26 23:20:00","passengers":209.0,"total_minutes":1467.0,"hours":0,"minutes":27,"time_combined":"0:27"}
{"origin_city":"Pearsonberg","dest_city":"Marieside","departure_date_time":"2020-11-09 07:57:00","arrival_date_time":"2020-11-10 23:45:00","passengers":733.0,"total_minutes":2388.0,"hours":15,"minutes":48,"time_combined":"15:48"}
{"origin_city":"Pearsonberg","dest_city":"New Karishire","departure_date_time":"2020-11-17 11:27:00","arrival_date_time":"2020-11-18 17:28:00","passengers":211.0,"total_minutes":1801.0,"hours":6,"minutes":1,"time_combined":"6:1"}
{"origin_city":"Pearsonberg","dest_city":"Currystad","departure_date_time":"2020-11-01 16:02:00","arrival_date_time":"2020-11-04 00:02:00","passengers":765.0,"total_minutes":3360.0,"hours":8,"minutes":0,"time_combined":"8:0"}
{"origin_city":"Pearsonberg","dest_city":"Santanaport","departure_date_time":"2020-11-29 09:49:00","arrival_date_time":"2020-12-01 14:49:00","passengers":740.0,"total_minutes":3180.0,"hours":5,"minutes":0,"time_combined":"5:0"}
{"origin_city":"Pearsonberg","dest_city":"New Cynthia","departure_date_time":"2020-11-05 05:28:00","arrival_date_time":"2020-11-07 08:52:00","passengers":640.0,"total_minutes":3084.0,"hours":3,"minutes":24,"time_combined":"3:24"}
{"origin_city":"Pearsonberg","dest_city":"Currystad","departure_date_time":"2020-11-19 17:44:00","arrival_date_time":"2020-11-20 18:33:00","passengers":745.0,"total_minutes":1489.0,"hours":0,"minutes":49,"time_combined":"0:49"}
{"origin_city":"Pearsonberg","dest_city":"West Charlesshire","departure_date_time":"2020-11-04 09:26:00","arrival_date_time":"2020-11-06 05:30:00","passengers":556.0,"total_minutes":2644.0,"hours":20,"minutes":4,"time_combined":"20:4"}
{"origin_city":"Pearsonberg","dest_city":"Keyberg","departure_date_time":"2020-11-09 08:25:00","arrival_date_time":"2020-11-11 10:24:00","passengers":497.0,"total_minutes":2999.0,"hours":1,"minutes":59,"time_combined":"1:59"}
{"origin_city":"Pearsonberg","dest_city":"Huntershire","departure_date_time":"2020-11-01 16:37:00","arrival_date_time":"2020-11-03 01:53:00","passengers":375.0,"total_minutes":1996.0,"hours":9,"minutes":16,"time_combined":"9:16"}
{"origin_city":"Pearsonberg","dest_city":"Timothyburgh","departure_date_time":"2020-11-23 01:07:00","arrival_date_time":"2020-11-24 02:18:00","passengers":489.0,"total_minutes":1511.0,"hours":1,"minutes":11,"time_combined":"1:11"}
